docs/conf.py
identity/__init__.py
identity/django.py
identity/flask.py
identity/pallet.py
identity/quart.py
identity/version.py
identity/web.py
identity/templates/identity/auth_error.html
identity/templates/identity/login.html
identity-0.11.0.dist-info/licenses/LICENSE
identity-0.11.0.dist-info/METADATA
identity-0.11.0.dist-info/WHEEL
identity-0.11.0.dist-info/top_level.txt
identity-0.11.0.dist-info/RECORD
