Metadata-Version: 2.4
Name: identity
Version: 0.11.0
Summary: This is an authentication/authorization library, currently optimized for web apps. It provides some higher level APIs built on top of Microsoft's MSAL Python.
Home-page: https://github.com/rayluo/identity
Author: Ray Luo
Author-email: rayluo.mba@gmail.com
License: MIT
Project-URL: Changelog, https://github.com/rayluo/identity/releases
Project-URL: Documentation, https://identity-library.readthedocs.io/
Keywords: identity,auth,authentication,authorization
Classifier: Development Status :: 4 - Beta
Classifier: License :: OSI Approved :: MIT License
Classifier: Operating System :: OS Independent
Classifier: Programming Language :: Python
Classifier: Programming Language :: Python :: 3
Classifier: Programming Language :: Python :: 3 :: Only
Classifier: Programming Language :: Python :: 3.8
Classifier: Programming Language :: Python :: 3.9
Classifier: Programming Language :: Python :: 3.10
Classifier: Programming Language :: Python :: 3.11
Classifier: Programming Language :: Python :: 3.12
Requires-Python: >=3.8
License-File: LICENSE
Requires-Dist: msal<2,>=1.28
Requires-Dist: requests<3,>=2.0.0
Provides-Extra: all-for-docs
Requires-Dist: django<6,>=3.2; extra == "all-for-docs"
Requires-Dist: flask; extra == "all-for-docs"
Requires-Dist: Flask-Session!=0.7.0,<0.9,>=0.3.2; extra == "all-for-docs"
Requires-Dist: quart; extra == "all-for-docs"
Requires-Dist: Quart-Session; extra == "all-for-docs"
Provides-Extra: django
Requires-Dist: django<6,>=3.2; extra == "django"
Provides-Extra: flask
Requires-Dist: flask; extra == "flask"
Requires-Dist: Flask-Session!=0.7.0,<0.9,>=0.3.2; extra == "flask"
Provides-Extra: quart
Requires-Dist: quart; extra == "quart"
Requires-Dist: Quart-Session; extra == "quart"
Dynamic: license-file
